{"cameraMode":{"drawMode":0,"name":"Shaded","section":"Shading Mode"},"sceneLighting":true,"audioPlay":false,"sceneViewState":{"m_AlwaysRefresh":false,"showFog":true,"showSkybox":true,"showFlares":true,"showImageEffects":true,"showParticleSystems":true,"showVisualEffectGraphs":true,"m_FxEnabled":true},"in2DMode":false,"pivot":{"x":371.17938232421877,"y":236.8619384765625,"z":603.8900146484375},"rotation":{"x":-0.012308391742408276,"y":0.012595889158546925,"z":-0.00015506488853134215,"w":-0.9998462200164795},"size":617.1450805664063,"orthographic":false}